location_field/__init__.py
location_field/apps.py
location_field/settings.py
location_field/urls.py
location_field/views.py
location_field/widgets.py
location_field/forms/__init__.py
location_field/forms/plain.py
location_field/forms/spatial.py
location_field/models/__init__.py
location_field/models/base.py
location_field/models/plain.py
location_field/models/spatial.py
location_field/static/location_field/l.control.geosearch.js
location_field/static/location_field/l.geosearch.provider.google.js
location_field/static/location_field/leaflet-google.js
location_field/static/location_field/leaflet.css
location_field/static/location_field/leaflet.js
location_field/static/location_field/images/layers-2x.png
location_field/static/location_field/images/layers.png
location_field/static/location_field/images/marker-icon-2x.png
location_field/static/location_field/images/marker-icon.png
location_field/static/location_field/images/marker-shadow.png
location_field/static/location_field/js/form.js
location_field/templates/location_field/map_widget.html
tests/__init__.py
tests/forms.py
tests/models.py
tests/spatial_models.py
tests/spatial_test.py
tests/test.py
tests/test_settings.py
django_location_field-2.1.1.dist-info/LICENSE
django_location_field-2.1.1.dist-info/METADATA
django_location_field-2.1.1.dist-info/WHEEL
django_location_field-2.1.1.dist-info/top_level.txt
django_location_field-2.1.1.dist-info/RECORD
